tree_plus_cli.py
tree_plus_src/__init__.py
tree_plus_src/count_tokens_lines.py
tree_plus_src/default_ignore.py
tree_plus_src/parse_file.py
tree_plus_src/traverse_directory.py
tree_plus_BIONICLES-1.0.0.dist-info/LICENSE
tree_plus_BIONICLES-1.0.0.dist-info/METADATA
tree_plus_BIONICLES-1.0.0.dist-info/WHEEL
tree_plus_BIONICLES-1.0.0.dist-info/entry_points.txt
tree_plus_BIONICLES-1.0.0.dist-info/top_level.txt
tree_plus_BIONICLES-1.0.0.dist-info/RECORD
