Metadata-Version: 2.1
Name: tree-plus-BIONICLES
Version: 1.0.0
Summary: tree util plus file components as leaves and token, line counts
Author-email: Bion Howard <bion@atomiclogic.com>
Project-URL: Homepage, https://github.com/bionicles/tree_plus
Project-URL: Issues, https://github.com/bionicles/tree_plus/issues
Project-URL: repository, https://www.github.com/bionicles/tree_plus
Project-URL: documentation, https://www.github.com/bionicles/tree_plus/README.md
Keywords: tree,util,cli
Classifier: Programming Language :: Python :: 3
Classifier: Topic :: Software Development :: Libraries :: Python Modules
Classifier: License :: OSI Approved :: Apache Software License
Classifier: License :: OSI Approved :: MIT License
Classifier: Operating System :: OS Independent
Classifier: Intended Audience :: Developers
Classifier: Topic :: Utilities
Requires-Python: >=3.8
License-File: LICENSE
Requires-Dist: tiktoken
Requires-Dist: PyYAML
Requires-Dist: pytest
Requires-Dist: click
Requires-Dist: rich
